autogen_gigachat/__init__.py
autogen_gigachat/_gigachat_client.py
autogen_gigachat/_model_info.py
autogen_gigachat/config/__init__.py
autogen_gigachat-0.1.1.dist-info/METADATA
autogen_gigachat-0.1.1.dist-info/WHEEL
autogen_gigachat-0.1.1.dist-info/licenses/LICENSE
autogen_gigachat-0.1.1.dist-info/RECORD
