Metadata-Version: 2.4
Name: autogen-gigachat
Version: 0.1.1
Summary: Gigachat client for autogen
License:     MIT License
License-File: LICENSE
Classifier: License :: OSI Approved :: MIT License
Classifier: Operating System :: OS Independent
Classifier: Programming Language :: Python :: 3
Requires-Python: >=3.10
Requires-Dist: autogen-core==0.6.1
Requires-Dist: gigachat==0.1.39post1
